<?xml version="1.0"?>
<!DOCTYPE hibernate-mapping PUBLIC "-//Hibernate/Hibernate Mapping DTD 3.0//EN"
"http://www.hibernate.org/dtd/hibernate-mapping-3.0.dtd">

<hibernate-mapping>
	<class name="com.maven.project.hib.model.Role" table="role_mstr"
		catalog="grey">
		<id name="roleId" type="string">
			<column name="ROLE_ID" length="30" />
			<generator class="assigned" />
		</id>
		<property name="description" type="string">
			<column name="DESCRIPTION" length="70" not-null="true" />
		</property>
	</class>
</hibernate-mapping>